st3g/St3g.py
st3g/__init__.py
st3g-0.0.1.dist-info/METADATA
st3g-0.0.1.dist-info/WHEEL
st3g-0.0.1.dist-info/licenses/LICENSE
st3g-0.0.1.dist-info/RECORD
